githubdata/__init__.py
githubdata/github_data_repo.py
githubdata/utils.py
githubdata-16.1.2.dist-info/METADATA
githubdata-16.1.2.dist-info/WHEEL
githubdata-16.1.2.dist-info/licenses/LICENSE
githubdata-16.1.2.dist-info/RECORD
