Metadata-Version: 2.1
Name: githubdata
Version: 16.1.2
Summary: A simple Python package to easily download from and manage a GitHub "Data repository"
Project-URL: Homepage, https://github.com/imahdimir/githubdata
Project-URL: Bug Tracker, https://github.com/imahdimir/githubdata/issues
Author-email: Mahdi Mir <imahdimir@gmail.com>
License: MIT License
License-File: LICENSE
Keywords: Finance,Stocks,TSE,Tehran,cleaning,data,data_cleaning
Classifier: Intended Audience :: Developers
Classifier: License :: OSI Approved :: MIT License
Classifier: Operating System :: OS Independent
Classifier: Programming Language :: Python :: 3
Classifier: Programming Language :: Python :: Implementation :: PyPy
Classifier: Topic :: Software Development :: Libraries :: Python Modules
Classifier: Topic :: Utilities
Requires-Dist: fastparquet
Requires-Dist: giteasy
Requires-Dist: pandas
Requires-Dist: pyarrow
